setup.py
ember_drf/__init__.py
ember_drf/compat.py
ember_drf/filters.py
ember_drf/parsers.py
ember_drf/renderers.py
ember_drf/serializers.py
ember_drf/utils.py
ember_drf/views.py
emberdrf.egg-info/PKG-INFO
emberdrf.egg-info/SOURCES.txt
emberdrf.egg-info/dependency_links.txt
emberdrf.egg-info/top_level.txt