Metadata-Version: 1.1
Name: emberdrf
Version: 0.1.8
Summary: Django Rest Framework addons to integrate with Ember.js
Home-page: https://github.com/g-cassie/ember-drf
Author: Gordon Cassie
Author-email: gordoncassie@gmail.com
License: BSD
Keywords: EmberJS Django REST
Platform: any
Classifier: Development Status :: 4 - Beta
Classifier: Framework :: Django
Classifier: Environment :: Web Environment
Classifier: License :: OSI Approved :: BSD License
Classifier: Intended Audience :: Developers
Classifier: Programming Language :: Python
Classifier: Programming Language :: Python :: 2.6
Classifier: Programming Language :: Python :: 2.7
Classifier: Topic :: Software Development :: Libraries :: Application Frameworks
Classifier: Topic :: Software Development :: Libraries :: Python Modules
